dbt_junitxml/main.py
dbt_junitxml-0.1.5.dist-info/entry_points.txt
dbt_junitxml-0.1.5.dist-info/LICENSE
dbt_junitxml-0.1.5.dist-info/WHEEL
dbt_junitxml-0.1.5.dist-info/METADATA
dbt_junitxml-0.1.5.dist-info/RECORD
