Metadata-Version: 2.1
Name: dbt-junitxml
Version: 0.1.5
Summary: 
Home-page: https://github.com/chasleslr/dbt-junitxml
License: MIT
Author: Charles Lariviere
Author-email: charleslariviere1@gmail.com
Requires-Python: >=3.7
Classifier: License :: OSI Approved :: MIT License
Classifier: Programming Language :: Python :: 3
Classifier: Programming Language :: Python :: 3.10
Classifier: Programming Language :: Python :: 3.7
Classifier: Programming Language :: Python :: 3.8
Classifier: Programming Language :: Python :: 3.9
Requires-Dist: click (>=8.1)
Requires-Dist: junit-xml (>=1.9)
Project-URL: Repository, https://github.com/chasleslr/dbt-junitxml
